webgatewayapi/__init__.py
webgatewayapi/actions.py
webgatewayapi/activities.py
webgatewayapi/appliances.py
webgatewayapi/authenticate.py
webgatewayapi/configuration.py
webgatewayapi/fileactions.py
webgatewayapi/listdata.py
webgatewayapi/parse.py
webgatewayapi/process.py
webgatewayapi/settings.py
webgatewayapi/systemfiles.py
webgatewayapi/tools.py
mcafee_mwgapi-0.3.dist-info/LICENSE
mcafee_mwgapi-0.3.dist-info/METADATA
mcafee_mwgapi-0.3.dist-info/WHEEL
mcafee_mwgapi-0.3.dist-info/top_level.txt
mcafee_mwgapi-0.3.dist-info/RECORD
