Metadata-Version: 2.1
Name: mcafee-mwgapi
Version: 0.3
Summary: Mcafee Web Gateway API functionality
Home-page: https://github.com/Ipv6Python/mcafee-mwgapi
Author: Ipv6Python
Author-email: ramipv6@gmail.com
License: MIT
Keywords: mcafee webgateway api development
Platform: UNKNOWN
Classifier: Programming Language :: Python :: 3
Classifier: License :: OSI Approved :: MIT License
Classifier: Operating System :: OS Independent
Requires-Python: >=3.4
